Patche/__init__.py
Patche/__main__.py
Patche/__version__.py
Patche/app.py
Patche/commands/apply.py
Patche/commands/help.py
Patche/commands/show.py
Patche/config.py
Patche/mcp/__init__.py
Patche/mcp/__main__.py
Patche/mcp/model.py
Patche/mcp/prompts.py
Patche/mcp/server.py
Patche/mcp/tools.py
Patche/model.py
Patche/utils/common.py
Patche/utils/header.py
Patche/utils/parse.py
Patche/utils/resolve.py
mseep_patche-1.0.1.dist-info/METADATA
mseep_patche-1.0.1.dist-info/WHEEL
mseep_patche-1.0.1.dist-info/entry_points.txt
mseep_patche-1.0.1.dist-info/licenses/LICENSE
mseep_patche-1.0.1.dist-info/RECORD
