Metadata-Version: 2.1
Name: mseep-patche
Version: 1.0.1
Summary: Modern Patch in Python
Author-Email: mseep <support@skydeck.ai>
License: MIT
Requires-Python: >=3.10
Requires-Dist: typer[all]>=0.9.0
Requires-Dist: pydantic>=2.5.3
Requires-Dist: pydantic-settings>=2.2.1
Requires-Dist: whatthepatch-pydantic==1.0.6a3
